pygam/__init__.py
pygam/callbacks.py
pygam/core.py
pygam/distributions.py
pygam/links.py
pygam/penalties.py
pygam/pygam.py
pygam/terms.py
pygam/utils.py
pygam/datasets/__init__.py
pygam/datasets/load_datasets.py
pygam/tests/__init__.py
pygam/tests/conftest.py
pygam/tests/test_GAM_methods.py
pygam/tests/test_GAM_params.py
pygam/tests/test_GAMs.py
pygam/tests/test_core.py
pygam/tests/test_datasets.py
pygam/tests/test_gridsearch.py
pygam/tests/test_partial_dependence.py
pygam/tests/test_penalties.py
pygam/tests/test_terms.py
pygam/tests/test_utils.py
pygam-0.10.0.dist-info/licenses/LICENSE
pygam-0.10.0.dist-info/METADATA
pygam-0.10.0.dist-info/WHEEL
pygam-0.10.0.dist-info/top_level.txt
pygam-0.10.0.dist-info/RECORD
