Metadata-Version: 2.4
Name: pygam
Version: 0.10.0
Summary: Generalized Additive Models in Python.
Author: Daniel Servén Marín, Charlie Brummitt
License: Apache-2.0
Requires-Python: <3.14,>=3.9
License-File: LICENSE
Requires-Dist: numpy>=1.5.0
Requires-Dist: progressbar2<5,>=4.2.0
Requires-Dist: scipy<1.17,>=1.11.1
Provides-Extra: dev
Requires-Dist: pandas>=1.6; extra == "dev"
Requires-Dist: pytest<8,>=7.2.2; extra == "dev"
Requires-Dist: flake8<7,>=6.0.0; extra == "dev"
Requires-Dist: codecov<3,>=2.1.12; extra == "dev"
Requires-Dist: pytest-cov<5,>=4.0.0; extra == "dev"
Requires-Dist: mock<6,>=5.0.1; extra == "dev"
Requires-Dist: nbsphinx<1,>=0.9.0; extra == "dev"
Requires-Dist: sphinx-rtd-theme<2,>=1.2.0; extra == "dev"
Requires-Dist: sphinxcontrib-napoleon<1,>=0.7; extra == "dev"
Requires-Dist: ipython<9,>=8.11.0; extra == "dev"
Requires-Dist: black<24,>=23.1.0; extra == "dev"
Dynamic: license-file
